LICENSE
README.md
pyproject.toml
setup.py
datalibrary/__init__.py
datalibrary/datasetcollection.py
datalibrary/downloader.py
datalibrary/pipeline.py
datalibrary/s3Client.py
datalibrary/util.py
examples/__init__.py
examples/object_detection/train.py
examples/object_detection/model/yolo.py
examples/object_detection/model/backbone/resnet.py
examples/object_detection/model/utils/modules.py
examples/object_detection/model/utils/tools.py
examples/scene_classification/train.py
examples/scene_classification/whurs19_json_writer.py
examples/scene_classification/whurs19_json_writer_from_s3.py
examples/scene_classification/model/__init__.py
examples/scene_classification/model/resnet.py
examples/scene_classification/model/train_and_valid.py
examples/scene_classification/utils/summaries.py
examples/semantic_segmentation/train.py
examples/semantic_segmentation/accVal/f1Score.py
examples/semantic_segmentation/modelNet/aspp.py
examples/semantic_segmentation/modelNet/deeplab_util.py
examples/semantic_segmentation/modelNet/deeplabv3.py
examples/semantic_segmentation/modelNet/resnet.py
pytdml/__init__.py
pytdml/config.py
pytdml/convert_utils.py
pytdml/tdml_image_crop.py
pytdml/utils.py
pytdml/yaml_to_tdml.py
pytdml/io/S3_reader.py
pytdml/io/__init__.py
pytdml/io/internal.py
pytdml/io/tdml_readers.py
pytdml/io/tdml_writers.py
pytdml/ml/__init__.py
pytdml/ml/ml_operators.py
pytdml/ml/object_transforms.py
pytdml/ml/tdml_tensorflow.py
pytdml/ml/tdml_torch.py
pytdml/ml/tdml_torch_data_pipe.py
pytdml/type/__init__.py
pytdml/type/_utils.py
pytdml/type/basic_types.py
pytdml/type/basic_types_old.py
pytdml/type/extended_types.py
pytdml/type/extended_types_old.py
pytdml/type/test.py
pytdml_zy.egg-info/PKG-INFO
pytdml_zy.egg-info/SOURCES.txt
pytdml_zy.egg-info/dependency_links.txt
pytdml_zy.egg-info/requires.txt
pytdml_zy.egg-info/top_level.txt
tests/__init__.py
tests/test_basic_types.py
tests/test_tdml_io.py