Metadata-Version: 2.1
Name: pytdml-zy
Version: 0.0.1
Summary: Parsing and encoding training datasets based on OGC Training Data Markup Language for AI (TrainingDML-AI) standard
Home-page: https://github.com/TrainingDML/pytdml
Author: Boyi Shangguan
Author-email: sgby@whu.edu.cn
License: MIT
Project-URL: homepage, https://github.com/TrainingDML/pytdml
Classifier: Development Status :: 3 - Alpha
Classifier: Intended Audience :: Developers
Classifier: Topic :: Scientific/Engineering :: GIS
Classifier: License :: OSI Approved :: MIT License
Classifier: Programming Language :: Python :: 3
License-File: LICENSE
Requires-Dist: geojson~=3.1.0
Requires-Dist: Pillow~=10.4.0
Requires-Dist: PyYAML~=6.0
Requires-Dist: numpy~=1.26.4
Requires-Dist: pandas~=2.2.2
Requires-Dist: opencv-python~=4.10.0.84
Requires-Dist: tensorflow~=2.17.0
Requires-Dist: jsonschema~=4.23.0
Requires-Dist: requests~=2.32.3
Requires-Dist: pydantic~=2.8.2
Requires-Dist: urllib3~=1.25.4
Requires-Dist: rasterio~=1.3.10
Requires-Dist: matplotlib~=3.9.1
Requires-Dist: minio~=7.2.7
Requires-Dist: tqdm~=4.66.4
Requires-Dist: s3fs~=2024.9.0
Provides-Extra: dev
Requires-Dist: pytest; extra == "dev"
Provides-Extra: torch
Requires-Dist: torch~=2.3.1; extra == "torch"
Requires-Dist: torchvision~=0.18.1; extra == "torch"
Requires-Dist: torchdata~=0.7.1; extra == "torch"
